.testr.conf
AUTHORS
ChangeLog
LICENSE
MANIFEST.in
README.rst
docs-requirements.txt
openstack-common.conf
requirements.txt
run_tests.sh
setup.cfg
setup.py
test-requirements.txt
tox.ini
automationclient/__init__.py
automationclient/base.py
automationclient/client.py
automationclient/exceptions.py
automationclient/extension.py
automationclient/service_catalog.py
automationclient/shell.py
automationclient/utils.py
automationclient/openstack/__init__.py
automationclient/openstack/common/__init__.py
automationclient/openstack/common/gettextutils.py
automationclient/openstack/common/importutils.py
automationclient/openstack/common/setup.py
automationclient/openstack/common/strutils.py
automationclient/openstack/common/version.py
automationclient/openstack/common/apiclient/__init__.py
automationclient/openstack/common/apiclient/auth.py
automationclient/openstack/common/apiclient/base.py
automationclient/openstack/common/apiclient/client.py
automationclient/openstack/common/apiclient/exceptions.py
automationclient/openstack/common/apiclient/fake_client.py
automationclient/tests/__init__.py
automationclient/tests/fakes.py
automationclient/tests/test_base.py
automationclient/tests/test_client.py
automationclient/tests/test_http.py
automationclient/tests/test_service_catalog.py
automationclient/tests/test_shell.py
automationclient/tests/test_utils.py
automationclient/tests/utils.py
automationclient/tests/v1_1/__init__.py
automationclient/tests/v1_1/fakes.py
automationclient/tests/v1_1/test_architectures.py
automationclient/tests/v1_1/test_auth.py
automationclient/tests/v1_1/test_components.py
automationclient/tests/v1_1/test_devices.py
automationclient/tests/v1_1/test_nodes.py
automationclient/tests/v1_1/test_profiles.py
automationclient/tests/v1_1/test_properties.py
automationclient/tests/v1_1/test_roles.py
automationclient/tests/v1_1/test_services.py
automationclient/tests/v1_1/test_shell.py
automationclient/tests/v1_1/test_zones.py
python_automationclient.egg-info/PKG-INFO
python_automationclient.egg-info/SOURCES.txt
python_automationclient.egg-info/dependency_links.txt
python_automationclient.egg-info/entry_points.txt
python_automationclient.egg-info/requires.txt
python_automationclient.egg-info/top_level.txt
