Metadata-Version: 1.1
Name: python-automationclient
Version: 1.2.1
Summary: Client library for StackOps Automation API.
Home-page: https://github.com/StackOps/python-automationclient
Author: StackOps Contributors
Author-email: developers@stackops.org
License: Apache License, Version 2.0
Platform: UNKNOWN
Classifier: Development Status :: 5 - Production/Stable
Classifier: Environment :: Console
Classifier: Intended Audience :: Developers
Classifier: Intended Audience :: Information Technology
Classifier: License :: OSI Approved :: Apache Software License
Classifier: Operating System :: OS Independent
Classifier: Programming Language :: Python
